adapter/__init__.py
adapter/mijia_adapter.py
config/__init__.py
config/mijia_config.py
mcp_server/__init__.py
mcp_server/mcp_server.py
mcp_server/mcp_test.py
mcp_server/server_config.json
miot_mcp-1.0.3.dist-info/licenses/LICENSE
utils/__init__.py
utils/auth_manager.py
utils/logger.py
miot_mcp-1.0.3.dist-info/METADATA
miot_mcp-1.0.3.dist-info/WHEEL
miot_mcp-1.0.3.dist-info/entry_points.txt
miot_mcp-1.0.3.dist-info/top_level.txt
miot_mcp-1.0.3.dist-info/RECORD
