Metadata-Version: 2.4
Name: miot-mcp
Version: 1.0.3
Summary: Mijia smart device MCP server, providing device discovery, property read/write, action invoke and other functions
Home-page: https://github.com/javen-yan/miot-mcp
Author: Javen Yan
Author-email: Javen Yan <2023335616@qq.com>
Project-URL: Homepage, https://github.com/javen-yan/miot-mcp
Project-URL: Bug Reports, https://github.com/javen-yan/miot-mcp/issues
Project-URL: Source, https://github.com/javen-yan/miot-mcp
Project-URL: Documentation, https://github.com/javen-yan/miot-mcp#readme
Keywords: xiaomi,mijia,iot,smart-home,mcp,automation
Classifier: Development Status :: 4 - Beta
Classifier: Intended Audience :: Developers
Classifier: License :: OSI Approved :: MIT License
Classifier: Operating System :: OS Independent
Classifier: Programming Language :: Python :: 3
Classifier: Programming Language :: Python :: 3.8
Classifier: Programming Language :: Python :: 3.9
Classifier: Programming Language :: Python :: 3.10
Classifier: Programming Language :: Python :: 3.11
Classifier: Programming Language :: Python :: 3.12
Classifier: Topic :: Home Automation
Classifier: Topic :: Software Development :: Libraries :: Python Modules
Requires-Python: >=3.8
License-File: LICENSE
Requires-Dist: mcp>=1.13.0
Requires-Dist: mijiaAPI>=2.0.1
Requires-Dist: Pillow>=10.0.0
Provides-Extra: dev
Requires-Dist: setuptools>=80.9.0; extra == "dev"
Requires-Dist: build; extra == "dev"
Requires-Dist: twine; extra == "dev"
Provides-Extra: docs
Requires-Dist: sphinx>=5.0.0; extra == "docs"
Requires-Dist: sphinx-rtd-theme>=1.0.0; extra == "docs"
Dynamic: author
Dynamic: home-page
Dynamic: license-file
Dynamic: requires-python
